{
  "kind": "singleType",
  "collectionName": "home_pages",
  "info": {
    "singularName": "home-page",
    "pluralName": "home-pages",
    "displayName": "Home Page"
  },
  "options": {
    "draftAndPublish": true
  },
  "pluginOptions": {},
  "attributes": {
    "banner_title": {
      "type": "string"
    },
    "banner_description": {
      "type": "text"
    },
    "banner_button_label": {
      "type": "string"
    },
    "banner_button_target": {
      "type": "string"
    },
    "banner_background_image": {
      "allowedTypes": [
        "images",
        "files",
        "videos",
        "audios"
      ],
      "type": "media",
      "multiple": false
    }
  }
}
